kubed/__init__.py
kubed/__main__.py
kubed/cli.py
kubed/main.py
kubed/aliases/aliases.sh
kubed/aliases/help_wrapper.sh
kubed/completions/bash/bash_completions.sh
kubed/completions/zsh/zsh_completions.sh
kubed-2.2.0.dist-info/METADATA
kubed-2.2.0.dist-info/WHEEL
kubed-2.2.0.dist-info/entry_points.txt
kubed-2.2.0.dist-info/top_level.txt
kubed-2.2.0.dist-info/RECORD
