Metadata-Version: 2.4
Name: kubed
Version: 2.2.0
Summary: A CLI tool for managing Kubernetes, Docker, Terraform, and Helm workflows
Home-page: https://cmds.daleyarborough.com
Author: Dale Yarborough
Author-email: Dale Yarborough <daleyarborough@gmail.com>
License: MIT
Project-URL: Homepage, https://cmds.daleyarborough.com
Project-URL: Repository, https://github.com/dalefrieswthat/kubed.git
Classifier: Development Status :: 5 - Production/Stable
Classifier: Intended Audience :: Developers
Classifier: License :: OSI Approved :: MIT License
Classifier: Operating System :: OS Independent
Classifier: Programming Language :: Python :: 3
Classifier: Programming Language :: Python :: 3.6
Classifier: Programming Language :: Python :: 3.7
Classifier: Programming Language :: Python :: 3.8
Classifier: Programming Language :: Python :: 3.9
Classifier: Programming Language :: Python :: 3.10
Classifier: Programming Language :: Python :: 3.11
Classifier: Topic :: Software Development :: Libraries :: Python Modules
Requires-Python: >=3.6
Requires-Dist: click
Requires-Dist: rich
Requires-Dist: pyyaml
Requires-Dist: requests
Requires-Dist: docker
Requires-Dist: kubernetes
Requires-Dist: helm
Dynamic: author
Dynamic: home-page
Dynamic: requires-python
